marketmanager/__init__.py
marketmanager/admin.py
marketmanager/admin_helpers.py
marketmanager/app_settings.py
marketmanager/apps.py
marketmanager/auth_hooks.py
marketmanager/buybacks.py
marketmanager/fittings.py
marketmanager/models.py
marketmanager/providers.py
marketmanager/task_helpers.py
marketmanager/tasks.py
marketmanager/urls.py
marketmanager/views.py
marketmanager/cogs/__init__.py
marketmanager/cogs/marketmanager.py
marketmanager/locale/de/LC_MESSAGES/django.mo
marketmanager/locale/de/LC_MESSAGES/django.po
marketmanager/locale/en/LC_MESSAGES/django.mo
marketmanager/locale/en/LC_MESSAGES/django.po
marketmanager/locale/es/LC_MESSAGES/django.mo
marketmanager/locale/es/LC_MESSAGES/django.po
marketmanager/locale/fr_FR/LC_MESSAGES/django.mo
marketmanager/locale/fr_FR/LC_MESSAGES/django.po
marketmanager/locale/it_IT/LC_MESSAGES/django.mo
marketmanager/locale/it_IT/LC_MESSAGES/django.po
marketmanager/locale/ja/LC_MESSAGES/django.mo
marketmanager/locale/ja/LC_MESSAGES/django.po
marketmanager/locale/ko_KR/LC_MESSAGES/django.mo
marketmanager/locale/ko_KR/LC_MESSAGES/django.po
marketmanager/locale/ru/LC_MESSAGES/django.mo
marketmanager/locale/ru/LC_MESSAGES/django.po
marketmanager/locale/ru_RU/LC_MESSAGES/django.mo
marketmanager/locale/ru_RU/LC_MESSAGES/django.po
marketmanager/locale/uk/LC_MESSAGES/django.mo
marketmanager/locale/uk/LC_MESSAGES/django.po
marketmanager/locale/zh_Hans/LC_MESSAGES/django.mo
marketmanager/locale/zh_Hans/LC_MESSAGES/django.po
marketmanager/management/commands/marketmanager_preload_common_eve_types.py
marketmanager/migrations/0001_initial.py
marketmanager/migrations/0001_squashed_0014_alter_privateconfig_valid_corporations_and_more.py
marketmanager/migrations/0002_alter_structure_created_at_alter_watchconfig_type.py
marketmanager/migrations/0002_auto_20211129_1339.py
marketmanager/migrations/0003_alter_general_options.py
marketmanager/migrations/0003_rename_type_watchconfig_eve_type.py
aa_market_manager-1.0.6.dist-info/licenses/LICENSE
aa_market_manager-1.0.6.dist-info/WHEEL
aa_market_manager-1.0.6.dist-info/METADATA
aa_market_manager-1.0.6.dist-info/RECORD
